elu_server/__init__.py
elu_server/main.py
server/__init__.py
server/main.py
elu_server-0.1.0.dist-info/LICENSE
elu_server-0.1.0.dist-info/METADATA
elu_server-0.1.0.dist-info/WHEEL
elu_server-0.1.0.dist-info/top_level.txt
elu_server-0.1.0.dist-info/RECORD
