Metadata-Version: 2.1
Name: elu-server
Version: 0.1.0
Summary: This package handle the communication between smartphone app and hardware module
Home-page: https://github.com/MaFa961/Eingebettete_Systeme_ELU_Server
Author: Marcel F
Author-email: marcel.fasterding@gmx.de
License: UNKNOWN
Platform: UNKNOWN
Classifier: Programming Language :: Python :: 3
Classifier: License :: OSI Approved :: MIT License
Classifier: Operating System :: OS Independent
